airflow_data_validation/__init__.py
airflow_data_validation/data_validation.py
airflow_data_validation/setup.py
airflow_data_validation-4.1.5.dist-info/WHEEL
airflow_data_validation-4.1.5.dist-info/METADATA
airflow_data_validation-4.1.5.dist-info/RECORD
