Metadata-Version: 2.1
Name: airflow-data-validation
Version: 4.1.5
Summary: 
Home-page: https://github.com/guestyorg/airflow_data_validation
Author: sapir.krespil
Author-email: sapir.krespil@guesty.com
Requires-Python: >=3.8
Classifier: Programming Language :: Python :: 3
Classifier: Programming Language :: Python :: 3.10
Classifier: Programming Language :: Python :: 3.8
Classifier: Programming Language :: Python :: 3.9
Requires-Dist: requests (>=2.0.0,<3.0.0)
Project-URL: Repository, https://github.com/guestyorg/airflow_data_validation
